cradle/__init__.py
cradle/cli.py
cradle/templates.yaml
cradle/utils/__init__.py
cradle/utils/git.py
cradle/utils/questions.py
cradle/utils/shell.py
repo_launcher-0.0.6.dist-info/METADATA
repo_launcher-0.0.6.dist-info/WHEEL
repo_launcher-0.0.6.dist-info/entry_points.txt
repo_launcher-0.0.6.dist-info/licenses/LICENSE
repo_launcher-0.0.6.dist-info/RECORD
