Metadata-Version: 2.4
Name: repo-launcher
Version: 0.0.6
Summary: CLI to create repos
Project-URL: repository, https://github.com/cvxgrp/cradle
Author-email: Thomas Schmelzer <thomas.schmelzer@gmail.com>
License-File: LICENSE
Requires-Python: >=3.10
Requires-Dist: copier>=9.3.1
Requires-Dist: fire>=0.7.0
Requires-Dist: loguru>=0.7.2
Requires-Dist: questionary>=2.0.1
